dpe_enedis_ademe_etl_engine/__init__.py
dpe_enedis_ademe_etl_engine/pipelines/__init__.py
dpe_enedis_ademe_etl_engine/pipelines/etl_app.py
dpe_enedis_ademe_etl_engine/scripts/__init__.py
dpe_enedis_ademe_etl_engine/scripts/envs_helper.py
dpe_enedis_ademe_etl_engine/scripts/extract.py
dpe_enedis_ademe_etl_engine/scripts/filestorage_helper.py
dpe_enedis_ademe_etl_engine/scripts/load.py
dpe_enedis_ademe_etl_engine/scripts/transform.py
dpe_enedis_ademe_etl_engine/utils/__init__.py
dpe_enedis_ademe_etl_engine/utils/fonctions.py
dpe_enedis_ademe_etl_engine-2.3.1.dist-info/licenses/LICENSE
dpe_enedis_ademe_etl_engine-2.3.1.dist-info/METADATA
dpe_enedis_ademe_etl_engine-2.3.1.dist-info/WHEEL
dpe_enedis_ademe_etl_engine-2.3.1.dist-info/top_level.txt
dpe_enedis_ademe_etl_engine-2.3.1.dist-info/RECORD
