Metadata-Version: 2.4
Name: dpe_enedis_ademe_etl_engine
Version: 2.3.1
Summary: Dataflows (ETL) backend for DPE Energy Performance Analysis.
Author-email: Féréol Gbenou <fereol.gbenou@ynov.com>
Project-URL: Issues, https://github.com/fereol023/DPE-Energy-Performance-Analysis-ETL.git
Requires-Python: >=3.11
License-File: LICENSE
Requires-Dist: httpx>=0.28.1
Requires-Dist: minio==7.2.15
Requires-Dist: numpy>=2.3.2
Requires-Dist: pandas>=2.3.1
Requires-Dist: pyyaml>=6.0.2
Requires-Dist: pyarrow==20.0.0
Requires-Dist: prefect==3.4.7
Requires-Dist: Requests==2.32.4
Requires-Dist: sqlalchemy
Requires-Dist: SQLAlchemy==2.0.41
Requires-Dist: unidecode>=1.4.0
Requires-Dist: yappi>=1.6.10
Requires-Dist: psycopg2-binary>=2.9.10
Requires-Dist: boto3>=1.40.16
Requires-Dist: click<8.2,>=8.0
Requires-Dist: fastapi>=0.116.1
Requires-Dist: pathlib>=1.0.1
Requires-Dist: prometheus-client>=0.22.1
Requires-Dist: psutil>=7.0.0
Requires-Dist: pydantic[email]>=2.11.7
Requires-Dist: pyjwt>=2.10.1
Requires-Dist: pytest>=8.4.1
Requires-Dist: python-multipart>=0.0.20
Requires-Dist: redis>=6.2.0
Requires-Dist: slowapi>=0.1.9
Requires-Dist: scikit-learn>=1.6.1
Requires-Dist: uvicorn>=0.35.0
Dynamic: license-file
